{
  "last_update": "2026-02-12T16:31:56.013489+00:00",
  "totalItems": 31,
  "indices": [
    {
      "ticker": "^GSPC",
      "name": "S&P 500",
      "price": 6856.3501,
      "trend": -1.23,
      "currency": null,
      "unit": "pts"
    },
    {
      "ticker": "^DJI",
      "name": "Dow Jones",
      "price": 49624.5781,
      "trend": -0.99,
      "currency": null,
      "unit": "pts"
    },
    {
      "ticker": "^IXIC",
      "name": "Nasdaq",
      "price": 22639.0273,
      "trend": -1.85,
      "currency": null,
      "unit": "pts"
    },
    {
      "ticker": "^STOXX50E",
      "name": "Euro Stoxx 50",
      "price": 6017.77,
      "trend": -0.3,
      "currency": null,
      "unit": "pts"
    },
    {
      "ticker": "^FTSE",
      "name": "FTSE 100",
      "price": 10412.5703,
      "trend": -0.57,
      "currency": null,
      "unit": "pts"
    },
    {
      "ticker": "^N225",
      "name": "Nikkei 225",
      "price": 57639.8398,
      "trend": -0.02,
      "currency": null,
      "unit": "pts"
    }
  ],
  "currencies": [
    {
      "ticker": "EURUSD=X",
      "name": "EUR / USD",
      "price": 1.1869,
      "trend": -0.17,
      "currency": null,
      "unit": null
    },
    {
      "ticker": "USDJPY=X",
      "name": "USD / JPY",
      "price": 152.515,
      "trend": -1.27,
      "currency": null,
      "unit": null
    },
    {
      "ticker": "GBPUSD=X",
      "name": "GBP / USD",
      "price": 1.3625,
      "trend": -0.07,
      "currency": null,
      "unit": null
    },
    {
      "ticker": "USDCNY=X",
      "name": "USD / CNY",
      "price": 6.9005,
      "trend": -0.15,
      "currency": null,
      "unit": null
    },
    {
      "ticker": "DX-Y.NYB",
      "name": "US Dollar Index",
      "price": 96.902,
      "trend": 0.07,
      "currency": null,
      "unit": "pts"
    },
    {
      "ticker": "USDMAD=X",
      "name": "USD / MAD",
      "price": 9.1373,
      "trend": 0.25,
      "currency": null,
      "unit": null
    },
    {
      "ticker": "EURMAD=X",
      "name": "EUR / MAD",
      "price": 10.828,
      "trend": 3.0,
      "currency": null,
      "unit": null
    },
    {
      "ticker": "GBPMAD=X",
      "name": "GBP / MAD",
      "price": 12.432,
      "trend": 3.06,
      "currency": null,
      "unit": null
    }
  ],
  "energy": [
    {
      "ticker": "BZ=F",
      "name": "Brent Crude",
      "price": 68.18,
      "trend": -1.76,
      "currency": "USD",
      "unit": "USD/bbl"
    },
    {
      "ticker": "CL=F",
      "name": "WTI Crude",
      "price": 63.46,
      "trend": -1.81,
      "currency": "USD",
      "unit": "USD/bbl"
    },
    {
      "ticker": "NG=F",
      "name": "Natural Gas",
      "price": 3.245,
      "trend": 2.72,
      "currency": "USD",
      "unit": "USD/MMBtu"
    },
    {
      "ticker": "HO=F",
      "name": "Heating Oil",
      "price": 2.408,
      "trend": -1.33,
      "currency": "USD",
      "unit": "USD/gal"
    },
    {
      "ticker": "RB=F",
      "name": "Gasoline (RBOB)",
      "price": 2.1556,
      "trend": 8.93,
      "currency": "USD",
      "unit": "USD/gal"
    }
  ],
  "metals": [
    {
      "ticker": "GC=F",
      "name": "Gold",
      "price": 4946.2998,
      "trend": -2.47,
      "currency": "USD",
      "unit": "USD/oz"
    },
    {
      "ticker": "SI=F",
      "name": "Silver",
      "price": 77.9,
      "trend": -6.99,
      "currency": "USD",
      "unit": "USD/oz"
    },
    {
      "ticker": "HG=F",
      "name": "Copper",
      "price": 5.8415,
      "trend": -1.81,
      "currency": "USD",
      "unit": "USD/lb"
    },
    {
      "ticker": "ALI=F",
      "name": "Aluminium",
      "price": 3059.5,
      "trend": 1.21,
      "currency": "USD",
      "unit": "USD/t"
    },
    {
      "ticker": "PL=F",
      "name": "Platinum",
      "price": 2030.9,
      "trend": -5.0,
      "currency": "USD",
      "unit": "USD/oz"
    },
    {
      "ticker": "PA=F",
      "name": "Palladium",
      "price": 1670.0,
      "trend": -3.76,
      "currency": "USD",
      "unit": "USD/oz"
    }
  ],
  "agriculture": [
    {
      "ticker": "SB=F",
      "name": "Sugar #11",
      "price": 13.47,
      "trend": -2.67,
      "currency": null,
      "unit": "¢/lb"
    },
    {
      "ticker": "KC=F",
      "name": "Coffee",
      "price": 298.3,
      "trend": 1.19,
      "currency": null,
      "unit": "¢/lb"
    },
    {
      "ticker": "CT=F",
      "name": "Cotton #2",
      "price": 64.12,
      "trend": 3.44,
      "currency": null,
      "unit": "¢/lb"
    },
    {
      "ticker": "ZW=F",
      "name": "Wheat",
      "price": 547.25,
      "trend": 1.86,
      "currency": null,
      "unit": "¢/bu"
    },
    {
      "ticker": "ZC=F",
      "name": "Corn",
      "price": 430.25,
      "trend": 0.64,
      "currency": null,
      "unit": "¢/bu"
    },
    {
      "ticker": "ZS=F",
      "name": "Soybeans",
      "price": 1139.5,
      "trend": 1.38,
      "currency": null,
      "unit": "¢/bu"
    }
  ],
  "rates": {
    "USD": 1.0,
    "EUR": 0.8425,
    "GBP": 0.7339,
    "JPY": 152.499,
    "CAD": 1.3626,
    "AUD": 1.4092,
    "CNY": 6.9005,
    "CHF": 0.7692,
    "HKD": 7.8164,
    "SGD": 1.262,
    "SEK": 8.9299,
    "KRW": 1438.51,
    "NOK": 9.5252,
    "NZD": 1.655,
    "INR": 90.571,
    "MXN": 17.2433,
    "TWD": 31.394,
    "ZAR": 15.9499,
    "BRL": 5.1966,
    "DKK": 6.2963,
    "PLN": 3.551,
    "THB": 31.04,
    "IDR": 16821.0,
    "HUF": 319.11,
    "CZK": 20.422,
    "ILS": 3.0711,
    "CLP": 856.58,
    "PHP": 58.075,
    "AED": 3.6729,
    "COP": 3670.75,
    "SAR": 3.7502,
    "MYR": 3.9,
    "RON": 4.29,
    "MAD": 9.1379
  },
  "exchanger_audit": {
    "total_requested": 33,
    "fetched": 33,
    "validated": 33,
    "bounds_rejected": [],
    "fetch_failed": [],
    "cross_check_deviations": {},
    "cross_check_source": "ECB",
    "final_count": 34
  }
}